[
    {
        "name": "1",
        "isHuman": false,
        "isAI": true,
        "original_name": "dalle3-00256"
    },
    {
        "name": "2",
        "isHuman": true,
        "isAI": false,
        "original_name": "n03388043_14254"
    },
    {
        "name": "3",
        "isHuman": false,
        "isAI": true,
        "original_name": "midjourney-00755"
    },
    {
        "name": "4",
        "isHuman": true,
        "isAI": false,
        "original_name": "n01751748_11072"
    },
    {
        "name": "5",
        "isHuman": true,
        "isAI": false,
        "original_name": "n01739381_5400"
    },
    {
        "name": "6",
        "isHuman": false,
        "isAI": true,
        "original_name": "midjourney-00513"
    },
    {
        "name": "7",
        "isHuman": false,
        "isAI": true,
        "original_name": "midjourney-01247"
    },
    {
        "name": "8",
        "isHuman": false,
        "isAI": true,
        "original_name": "midjourney-00742"
    },
    {
        "name": "9",
        "isHuman": false,
        "isAI": true,
        "original_name": "dalle3-00827"
    },
    {
        "name": "10",
        "isHuman": false,
        "isAI": true,
        "original_name": "midjourney-00212"
    },
    {
        "name": "11",
        "isHuman": false,
        "isAI": true,
        "original_name": "dalle3-00161"
    },
    {
        "name": "12",
        "isHuman": false,
        "isAI": true,
        "original_name": "midjourney-01170"
    },
    {
        "name": "13",
        "isHuman": false,
        "isAI": true,
        "original_name": "midjourney-00725"
    },
    {
        "name": "14",
        "isHuman": false,
        "isAI": true,
        "original_name": "dalle3-00317"
    },
    {
        "name": "15",
        "isHuman": false,
        "isAI": true,
        "original_name": "dalle3-01627"
    },
    {
        "name": "16",
        "isHuman": true,
        "isAI": false,
        "original_name": "n04192698_64309"
    },
    {
        "name": "17",
        "isHuman": false,
        "isAI": true,
        "original_name": "dalle3-00172"
    },
    {
        "name": "18",
        "isHuman": false,
        "isAI": true,
        "original_name": "dalle3-01582"
    },
    {
        "name": "19",
        "isHuman": true,
        "isAI": false,
        "original_name": "n02480495_4103"
    },
    {
        "name": "20",
        "isHuman": true,
        "isAI": false,
        "original_name": "n01632777_11702"
    },
    {
        "name": "21",
        "isHuman": true,
        "isAI": false,
        "original_name": "0049x4"
    },
    {
        "name": "22",
        "isHuman": false,
        "isAI": true,
        "original_name": "midjourney-00554"
    },
    {
        "name": "23",
        "isHuman": false,
        "isAI": true,
        "original_name": "dalle3-01200"
    },
    {
        "name": "24",
        "isHuman": false,
        "isAI": true,
        "original_name": "midjourney-00707"
    },
    {
        "name": "25",
        "isHuman": true,
        "isAI": false,
        "original_name": "n07717410_3078"
    },
    {
        "name": "26",
        "isHuman": false,
        "isAI": true,
        "original_name": "dalle3-00295"
    },
    {
        "name": "27",
        "isHuman": false,
        "isAI": true,
        "original_name": "dalle3-00468"
    },
    {
        "name": "28",
        "isHuman": true,
        "isAI": false,
        "original_name": "n02870880_12220"
    },
    {
        "name": "29",
        "isHuman": false,
        "isAI": true,
        "original_name": "midjourney-00226"
    },
    {
        "name": "30",
        "isHuman": true,
        "isAI": false,
        "original_name": "0159x4"
    },
    {
        "name": "31",
        "isHuman": false,
        "isAI": true,
        "original_name": "dalle3-01730"
    },
    {
        "name": "32",
        "isHuman": true,
        "isAI": false,
        "original_name": "0015x4"
    },
    {
        "name": "33",
        "isHuman": true,
        "isAI": false,
        "original_name": "n09399592_34596"
    },
    {
        "name": "34",
        "isHuman": false,
        "isAI": true,
        "original_name": "dalle3-00257"
    },
    {
        "name": "35",
        "isHuman": true,
        "isAI": false,
        "original_name": "n02087046_12437"
    },
    {
        "name": "36",
        "isHuman": true,
        "isAI": false,
        "original_name": "n03666591_32958"
    },
    {
        "name": "37",
        "isHuman": false,
        "isAI": true,
        "original_name": "midjourney-01349"
    },
    {
        "name": "38",
        "isHuman": true,
        "isAI": false,
        "original_name": "0596x4"
    },
    {
        "name": "39",
        "isHuman": false,
        "isAI": true,
        "original_name": "dalle3-01150"
    },
    {
        "name": "40",
        "isHuman": true,
        "isAI": false,
        "original_name": "n01748264_21510"
    },
    {
        "name": "41",
        "isHuman": true,
        "isAI": false,
        "original_name": "n02093428_1301"
    },
    {
        "name": "42",
        "isHuman": false,
        "isAI": true,
        "original_name": "dalle3-00805"
    },
    {
        "name": "43",
        "isHuman": true,
        "isAI": false,
        "original_name": "0791x4"
    },
    {
        "name": "44",
        "isHuman": true,
        "isAI": false,
        "original_name": "n02494079_3545"
    },
    {
        "name": "45",
        "isHuman": true,
        "isAI": false,
        "original_name": "n02087394_2976"
    },
    {
        "name": "46",
        "isHuman": true,
        "isAI": false,
        "original_name": "0248x4"
    },
    {
        "name": "47",
        "isHuman": true,
        "isAI": false,
        "original_name": "n02776631_6500"
    },
    {
        "name": "48",
        "isHuman": true,
        "isAI": false,
        "original_name": "0770x4"
    },
    {
        "name": "49",
        "isHuman": false,
        "isAI": true,
        "original_name": "dalle3-01716"
    },
    {
        "name": "50",
        "isHuman": true,
        "isAI": false,
        "original_name": "n02317335_6058"
    },
    {
        "name": "51",
        "isHuman": true,
        "isAI": false,
        "original_name": "0325x4"
    },
    {
        "name": "52",
        "isHuman": false,
        "isAI": true,
        "original_name": "dalle3-00582"
    },
    {
        "name": "53",
        "isHuman": true,
        "isAI": false,
        "original_name": "n01443537_7582"
    },
    {
        "name": "54",
        "isHuman": false,
        "isAI": true,
        "original_name": "dalle3-01587"
    },
    {
        "name": "55",
        "isHuman": true,
        "isAI": false,
        "original_name": "0526x4"
    },
    {
        "name": "56",
        "isHuman": false,
        "isAI": true,
        "original_name": "midjourney-00531"
    },
    {
        "name": "57",
        "isHuman": true,
        "isAI": false,
        "original_name": "0590x4"
    },
    {
        "name": "58",
        "isHuman": false,
        "isAI": true,
        "original_name": "dalle3-00538"
    },
    {
        "name": "59",
        "isHuman": false,
        "isAI": true,
        "original_name": "dalle3-00092"
    },
    {
        "name": "60",
        "isHuman": true,
        "isAI": false,
        "original_name": "n02091032_1871"
    },
    {
        "name": "61",
        "isHuman": true,
        "isAI": false,
        "original_name": "n07717410_91"
    },
    {
        "name": "62",
        "isHuman": true,
        "isAI": false,
        "original_name": "n02108551_10170"
    },
    {
        "name": "63",
        "isHuman": true,
        "isAI": false,
        "original_name": "0525x4"
    },
    {
        "name": "64",
        "isHuman": true,
        "isAI": false,
        "original_name": "n03670208_33101"
    },
    {
        "name": "65",
        "isHuman": false,
        "isAI": true,
        "original_name": "midjourney-01208"
    },
    {
        "name": "66",
        "isHuman": true,
        "isAI": false,
        "original_name": "0370x4"
    },
    {
        "name": "67",
        "isHuman": false,
        "isAI": true,
        "original_name": "midjourney-00559"
    },
    {
        "name": "68",
        "isHuman": false,
        "isAI": true,
        "original_name": "midjourney-00466"
    },
    {
        "name": "69",
        "isHuman": false,
        "isAI": true,
        "original_name": "dalle3-01227"
    },
    {
        "name": "70",
        "isHuman": false,
        "isAI": true,
        "original_name": "dalle3-00479"
    },
    {
        "name": "71",
        "isHuman": true,
        "isAI": false,
        "original_name": "n03026506_4314"
    },
    {
        "name": "72",
        "isHuman": true,
        "isAI": false,
        "original_name": "n01537544_16043"
    },
    {
        "name": "73",
        "isHuman": false,
        "isAI": true,
        "original_name": "dalle3-01513"
    },
    {
        "name": "74",
        "isHuman": false,
        "isAI": true,
        "original_name": "dalle3-01667"
    },
    {
        "name": "75",
        "isHuman": true,
        "isAI": false,
        "original_name": "n04243546_8449"
    },
    {
        "name": "76",
        "isHuman": false,
        "isAI": true,
        "original_name": "midjourney-00638"
    },
    {
        "name": "77",
        "isHuman": false,
        "isAI": true,
        "original_name": "dalle3-01458"
    },
    {
        "name": "78",
        "isHuman": false,
        "isAI": true,
        "original_name": "dalle3-01476"
    },
    {
        "name": "79",
        "isHuman": false,
        "isAI": true,
        "original_name": "dalle3-01159"
    },
    {
        "name": "80",
        "isHuman": false,
        "isAI": true,
        "original_name": "dalle3-01538"
    },
    {
        "name": "81",
        "isHuman": true,
        "isAI": false,
        "original_name": "n02483708_2360"
    },
    {
        "name": "82",
        "isHuman": false,
        "isAI": true,
        "original_name": "midjourney-01217"
    },
    {
        "name": "83",
        "isHuman": false,
        "isAI": true,
        "original_name": "midjourney-00636"
    },
    {
        "name": "84",
        "isHuman": true,
        "isAI": false,
        "original_name": "n03062245_5351"
    },
    {
        "name": "85",
        "isHuman": true,
        "isAI": false,
        "original_name": "n03124170_931"
    },
    {
        "name": "86",
        "isHuman": false,
        "isAI": true,
        "original_name": "dalle3-00141"
    },
    {
        "name": "87",
        "isHuman": true,
        "isAI": false,
        "original_name": "n02088238_6257"
    },
    {
        "name": "88",
        "isHuman": true,
        "isAI": false,
        "original_name": "n04356056_64610"
    },
    {
        "name": "89",
        "isHuman": true,
        "isAI": false,
        "original_name": "n03623198_7094"
    },
    {
        "name": "90",
        "isHuman": true,
        "isAI": false,
        "original_name": "n01817953_9276"
    },
    {
        "name": "91",
        "isHuman": false,
        "isAI": true,
        "original_name": "dalle3-00178"
    },
    {
        "name": "92",
        "isHuman": false,
        "isAI": true,
        "original_name": "midjourney-00456"
    },
    {
        "name": "93",
        "isHuman": false,
        "isAI": true,
        "original_name": "dalle3-01400"
    },
    {
        "name": "94",
        "isHuman": true,
        "isAI": false,
        "original_name": "0785x4"
    },
    {
        "name": "95",
        "isHuman": true,
        "isAI": false,
        "original_name": "0589x4"
    },
    {
        "name": "96",
        "isHuman": true,
        "isAI": false,
        "original_name": "n03345487_20792"
    },
    {
        "name": "97",
        "isHuman": false,
        "isAI": true,
        "original_name": "midjourney-00042"
    },
    {
        "name": "98",
        "isHuman": true,
        "isAI": false,
        "original_name": "n02095570_11864"
    },
    {
        "name": "99",
        "isHuman": false,
        "isAI": true,
        "original_name": "dalle3-01700"
    },
    {
        "name": "100",
        "isHuman": false,
        "isAI": true,
        "original_name": "dalle3-01631"
    },
    {
        "name": "101",
        "isHuman": true,
        "isAI": false,
        "original_name": "n02640242_6281"
    },
    {
        "name": "102",
        "isHuman": true,
        "isAI": false,
        "original_name": "n02342885_4776"
    },
    {
        "name": "103",
        "isHuman": false,
        "isAI": true,
        "original_name": "midjourney-00841"
    },
    {
        "name": "104",
        "isHuman": false,
        "isAI": true,
        "original_name": "midjourney-00249"
    },
    {
        "name": "105",
        "isHuman": false,
        "isAI": true,
        "original_name": "midjourney-00601"
    },
    {
        "name": "106",
        "isHuman": true,
        "isAI": false,
        "original_name": "n04456115_8889"
    },
    {
        "name": "107",
        "isHuman": false,
        "isAI": true,
        "original_name": "dalle3-00328"
    },
    {
        "name": "108",
        "isHuman": true,
        "isAI": false,
        "original_name": "n02979186_21024"
    },
    {
        "name": "109",
        "isHuman": false,
        "isAI": true,
        "original_name": "midjourney-00221"
    },
    {
        "name": "110",
        "isHuman": true,
        "isAI": false,
        "original_name": "0117x4"
    },
    {
        "name": "111",
        "isHuman": true,
        "isAI": false,
        "original_name": "n02106382_3571"
    },
    {
        "name": "112",
        "isHuman": false,
        "isAI": true,
        "original_name": "midjourney-00565"
    },
    {
        "name": "113",
        "isHuman": true,
        "isAI": false,
        "original_name": "0097x4"
    },
    {
        "name": "114",
        "isHuman": true,
        "isAI": false,
        "original_name": "n04311174_6332"
    },
    {
        "name": "115",
        "isHuman": false,
        "isAI": true,
        "original_name": "midjourney-00640"
    },
    {
        "name": "116",
        "isHuman": true,
        "isAI": false,
        "original_name": "n03814639_1179"
    },
    {
        "name": "117",
        "isHuman": false,
        "isAI": true,
        "original_name": "midjourney-01207"
    },
    {
        "name": "118",
        "isHuman": false,
        "isAI": true,
        "original_name": "midjourney-01286"
    },
    {
        "name": "119",
        "isHuman": true,
        "isAI": false,
        "original_name": "n04070727_78904"
    },
    {
        "name": "120",
        "isHuman": true,
        "isAI": false,
        "original_name": "n03065424_3994"
    },
    {
        "name": "121",
        "isHuman": false,
        "isAI": true,
        "original_name": "midjourney-00956"
    },
    {
        "name": "122",
        "isHuman": false,
        "isAI": true,
        "original_name": "dalle3-00788"
    },
    {
        "name": "123",
        "isHuman": true,
        "isAI": false,
        "original_name": "n03733131_13817"
    },
    {
        "name": "124",
        "isHuman": false,
        "isAI": true,
        "original_name": "dalle3-00619"
    },
    {
        "name": "125",
        "isHuman": false,
        "isAI": true,
        "original_name": "midjourney-00792"
    },
    {
        "name": "126",
        "isHuman": false,
        "isAI": true,
        "original_name": "midjourney-00599"
    },
    {
        "name": "127",
        "isHuman": false,
        "isAI": true,
        "original_name": "dalle3-00583"
    },
    {
        "name": "128",
        "isHuman": false,
        "isAI": true,
        "original_name": "midjourney-00502"
    },
    {
        "name": "129",
        "isHuman": false,
        "isAI": true,
        "original_name": "midjourney-00199"
    },
    {
        "name": "130",
        "isHuman": false,
        "isAI": true,
        "original_name": "midjourney-01192"
    },
    {
        "name": "131",
        "isHuman": true,
        "isAI": false,
        "original_name": "n04562935_5265"
    },
    {
        "name": "132",
        "isHuman": false,
        "isAI": true,
        "original_name": "midjourney-00783"
    },
    {
        "name": "133",
        "isHuman": false,
        "isAI": true,
        "original_name": "midjourney-00483"
    },
    {
        "name": "134",
        "isHuman": true,
        "isAI": false,
        "original_name": "n02106030_8898"
    },
    {
        "name": "135",
        "isHuman": true,
        "isAI": false,
        "original_name": "n03444034_968"
    },
    {
        "name": "136",
        "isHuman": false,
        "isAI": true,
        "original_name": "midjourney-01317"
    },
    {
        "name": "137",
        "isHuman": false,
        "isAI": true,
        "original_name": "dalle3-00653"
    },
    {
        "name": "138",
        "isHuman": false,
        "isAI": true,
        "original_name": "dalle3-00449"
    },
    {
        "name": "139",
        "isHuman": false,
        "isAI": true,
        "original_name": "midjourney-00786"
    },
    {
        "name": "140",
        "isHuman": true,
        "isAI": false,
        "original_name": "n01531178_20485"
    },
    {
        "name": "141",
        "isHuman": true,
        "isAI": false,
        "original_name": "n03179701_1062"
    },
    {
        "name": "142",
        "isHuman": false,
        "isAI": true,
        "original_name": "dalle3-00259"
    },
    {
        "name": "143",
        "isHuman": false,
        "isAI": true,
        "original_name": "dalle3-00341"
    },
    {
        "name": "144",
        "isHuman": false,
        "isAI": true,
        "original_name": "midjourney-00175"
    },
    {
        "name": "145",
        "isHuman": false,
        "isAI": true,
        "original_name": "midjourney-00757"
    },
    {
        "name": "146",
        "isHuman": true,
        "isAI": false,
        "original_name": "0108x4"
    },
    {
        "name": "147",
        "isHuman": true,
        "isAI": false,
        "original_name": "n04086273_6886"
    },
    {
        "name": "148",
        "isHuman": false,
        "isAI": true,
        "original_name": "dalle3-01347"
    },
    {
        "name": "149",
        "isHuman": false,
        "isAI": true,
        "original_name": "midjourney-00223"
    },
    {
        "name": "150",
        "isHuman": false,
        "isAI": true,
        "original_name": "dalle3-01646"
    },
    {
        "name": "151",
        "isHuman": true,
        "isAI": false,
        "original_name": "n03887697_2471"
    },
    {
        "name": "152",
        "isHuman": false,
        "isAI": true,
        "original_name": "dalle3-01552"
    },
    {
        "name": "153",
        "isHuman": true,
        "isAI": false,
        "original_name": "n02017213_2344"
    },
    {
        "name": "154",
        "isHuman": true,
        "isAI": false,
        "original_name": "n03255030_874"
    },
    {
        "name": "155",
        "isHuman": true,
        "isAI": false,
        "original_name": "n02018207_44448"
    },
    {
        "name": "156",
        "isHuman": false,
        "isAI": true,
        "original_name": "midjourney-00947"
    },
    {
        "name": "157",
        "isHuman": false,
        "isAI": true,
        "original_name": "dalle3-00469"
    },
    {
        "name": "158",
        "isHuman": true,
        "isAI": false,
        "original_name": "n01749939_6646"
    },
    {
        "name": "159",
        "isHuman": true,
        "isAI": false,
        "original_name": "n02825657_11982"
    },
    {
        "name": "160",
        "isHuman": true,
        "isAI": false,
        "original_name": "n02526121_1785"
    },
    {
        "name": "161",
        "isHuman": false,
        "isAI": true,
        "original_name": "dalle3-00450"
    },
    {
        "name": "162",
        "isHuman": true,
        "isAI": false,
        "original_name": "n01740131_14858"
    },
    {
        "name": "163",
        "isHuman": false,
        "isAI": true,
        "original_name": "dalle3-00185"
    },
    {
        "name": "164",
        "isHuman": true,
        "isAI": false,
        "original_name": "n01532829_1332"
    },
    {
        "name": "165",
        "isHuman": true,
        "isAI": false,
        "original_name": "n09229709_42465"
    },
    {
        "name": "166",
        "isHuman": true,
        "isAI": false,
        "original_name": "n03891332_5511"
    },
    {
        "name": "167",
        "isHuman": true,
        "isAI": false,
        "original_name": "n02364673_17458"
    },
    {
        "name": "168",
        "isHuman": true,
        "isAI": false,
        "original_name": "0779x4"
    },
    {
        "name": "169",
        "isHuman": true,
        "isAI": false,
        "original_name": "n03127747_3481"
    },
    {
        "name": "170",
        "isHuman": true,
        "isAI": false,
        "original_name": "n03534580_6564"
    },
    {
        "name": "171",
        "isHuman": true,
        "isAI": false,
        "original_name": "n04238763_9942"
    },
    {
        "name": "172",
        "isHuman": false,
        "isAI": true,
        "original_name": "dalle3-00485"
    },
    {
        "name": "173",
        "isHuman": true,
        "isAI": false,
        "original_name": "n03259280_6695"
    },
    {
        "name": "174",
        "isHuman": false,
        "isAI": true,
        "original_name": "dalle3-00743"
    },
    {
        "name": "175",
        "isHuman": true,
        "isAI": false,
        "original_name": "n02437312_4121"
    },
    {
        "name": "176",
        "isHuman": true,
        "isAI": false,
        "original_name": "n01664065_10873"
    },
    {
        "name": "177",
        "isHuman": true,
        "isAI": false,
        "original_name": "n02077923_14621"
    },
    {
        "name": "178",
        "isHuman": true,
        "isAI": false,
        "original_name": "n07749582_16429"
    },
    {
        "name": "179",
        "isHuman": false,
        "isAI": true,
        "original_name": "midjourney-00525"
    },
    {
        "name": "180",
        "isHuman": true,
        "isAI": false,
        "original_name": "n02127052_8034"
    },
    {
        "name": "181",
        "isHuman": true,
        "isAI": false,
        "original_name": "n03180011_8668"
    },
    {
        "name": "182",
        "isHuman": false,
        "isAI": true,
        "original_name": "midjourney-00931"
    },
    {
        "name": "183",
        "isHuman": true,
        "isAI": false,
        "original_name": "n02169497_6916"
    },
    {
        "name": "184",
        "isHuman": false,
        "isAI": true,
        "original_name": "midjourney-00562"
    },
    {
        "name": "185",
        "isHuman": false,
        "isAI": true,
        "original_name": "dalle3-00534"
    },
    {
        "name": "186",
        "isHuman": true,
        "isAI": false,
        "original_name": "n03857828_54630"
    },
    {
        "name": "187",
        "isHuman": true,
        "isAI": false,
        "original_name": "0783x4"
    },
    {
        "name": "188",
        "isHuman": false,
        "isAI": true,
        "original_name": "midjourney-00521"
    },
    {
        "name": "189",
        "isHuman": true,
        "isAI": false,
        "original_name": "0604x4"
    },
    {
        "name": "190",
        "isHuman": false,
        "isAI": true,
        "original_name": "midjourney-00700"
    },
    {
        "name": "191",
        "isHuman": true,
        "isAI": false,
        "original_name": "n02058221_3390"
    },
    {
        "name": "192",
        "isHuman": false,
        "isAI": true,
        "original_name": "dalle3-00277"
    },
    {
        "name": "193",
        "isHuman": true,
        "isAI": false,
        "original_name": "n03272010_6810"
    },
    {
        "name": "194",
        "isHuman": true,
        "isAI": false,
        "original_name": "n02233338_21963"
    },
    {
        "name": "195",
        "isHuman": true,
        "isAI": false,
        "original_name": "n04081281_13932"
    },
    {
        "name": "196",
        "isHuman": false,
        "isAI": true,
        "original_name": "midjourney-00537"
    },
    {
        "name": "197",
        "isHuman": false,
        "isAI": true,
        "original_name": "dalle3-00263"
    },
    {
        "name": "198",
        "isHuman": false,
        "isAI": true,
        "original_name": "midjourney-00176"
    },
    {
        "name": "199",
        "isHuman": true,
        "isAI": false,
        "original_name": "n03676483_17817"
    },
    {
        "name": "200",
        "isHuman": true,
        "isAI": false,
        "original_name": "n03584254_2244"
    }
]